README.md
setup.py
snnpy/__init__.py
snnpy/snn.py
snnpy.egg-info/PKG-INFO
snnpy.egg-info/SOURCES.txt
snnpy.egg-info/dependency_links.txt
snnpy.egg-info/requires.txt
snnpy.egg-info/top_level.txt